[
  {
    "username": "raju1990",
    "password": "raju@123",
    "secret_question": "What is your mother's maiden name?",
    "secret_answer": "Patel"
  },
  {
    "username": "meena_sharma",
    "password": "meena@2022",
    "secret_question": "What is your favorite childhood nickname?",
    "secret_answer": "Mona"
  },
  {
    "username": "amit_delhi",
    "password": "amit1234",
    "secret_question": "What is your favorite food?",
    "secret_answer": "Paneer Tikka"
  },
  {
    "username": "deepa_mumbai",
    "password": "deepa@789",
    "secret_question": "What is the name of your first pet?",
    "secret_answer": "Tommy"
  },
  {
    "username": "arjun_bangalore",
    "password": "arjun@567",
    "secret_question": "What is your favorite holiday destination?",
    "secret_answer": "Goa"
  },
  {
    "username": "Aditi_singh",
    "password": "aditi",
    "secret_question": "who is my roommate?",
    "secret_answer": "arya suwalka"
  },
  {
    "username": "arya_suwalka",
    "password": "aryaaaa",
    "secret_question": "what is your favourite food?",
    "secret_answer": "Paneer"
  },
  {
    "username": "kforkavya",
    "password": "kforkavya",
    "secret_question": "Are you Anon Mouse on Piazza ?",
    "secret_answer": "Yes"
  },
  {
    "username": "Aakash Gupta",
    "password": "asdfgh",
    "secret_question": "who is my roommate?",
    "secret_answer": "turtle"
  },
  {
    "username": "jigyasa",
    "password": "whoknows",
    "secret_question": "who is my roommate?",
    "secret_answer": "gowri"
  },
  {
    "username": "sanchita",
    "password": "sanchita",
    "secret_question": "sanchita",
    "secret_answer": "sanchita"
  },
  {
    "username": "Abhilasha",
    "password": "WHyHell1207",
    "secret_question": "Why am I single ?",
    "secret_answer": "Yes"
  },
  {
    "username": "Ram",
    "password": "hi",
    "secret_question": "who troubles me the most",
    "secret_answer": "abhilasha"
  },
  {
    "username": "Rizzi Kalra",
    "password": "1234",
    "secret_question": "name?",
    "secret_answer": "Rishi Kalra"
  },
  {
    "username": "suman",
    "password": "suman",
    "secret_question": "what is your favourite food?",
    "secret_answer": "Dal-chawal"
  }
]